mkdocs_curriculum_vitae/404.html
mkdocs_curriculum_vitae/__init__.py
mkdocs_curriculum_vitae/head.html
mkdocs_curriculum_vitae/main.html
mkdocs_curriculum_vitae/mkdocs_theme.yml
mkdocs_curriculum_vitae/scripts.html
mkdocs_curriculum_vitae/assets/mkdocs_curriculum_vitae.css
mkdocs_curriculum_vitae/assets/fonts/PressStart2P-Regular.ttf
mkdocs_curriculum_vitae/assets/layouts/default.css
mkdocs_curriculum_vitae/assets/layouts/vertical.css
mkdocs_curriculum_vitae/assets/themes/default.css
mkdocs_curriculum_vitae/assets/themes/minimalist.css
mkdocs_curriculum_vitae/assets/themes/neon.css
mkdocs_curriculum_vitae/assets/themes/nes.css
mkdocs_curriculum_vitae-0.12.1.dist-info/licenses/LICENSE
mkdocs_curriculum_vitae-0.12.1.dist-info/METADATA
mkdocs_curriculum_vitae-0.12.1.dist-info/WHEEL
mkdocs_curriculum_vitae-0.12.1.dist-info/entry_points.txt
mkdocs_curriculum_vitae-0.12.1.dist-info/top_level.txt
mkdocs_curriculum_vitae-0.12.1.dist-info/RECORD
