Metadata-Version: 2.4
Name: mkdocs-curriculum-vitae
Version: 0.12.1
Summary: MkDocs Theme for curriculum vitae
Author-email: Paul Riviere <paolo3799@gmail.com>
License: MIT License
Project-URL: Documentation, https://paul-riviere.github.io/mkdocs-curriculum-vitae/
Project-URL: Issues, https://github.com/Paul-Riviere/mkdocs-curriculum-vitae/issues
Project-URL: Source, https://github.com/Paul-Riviere/mkdocs-curriculum-vitae
Classifier: Development Status :: 3 - Alpha
Classifier: Environment :: Console
Classifier: Operating System :: POSIX
Classifier: Intended Audience :: Developers
Classifier: Intended Audience :: Information Technology
Classifier: Intended Audience :: System Administrators
Classifier: Topic :: Software Development :: Build Tools
Classifier: Natural Language :: English
Classifier: Programming Language :: Python :: 3.9
Classifier: Topic :: Utilities
Classifier: Topic :: Software Development :: Documentation
Requires-Python: >=3.9
License-File: LICENSE
Requires-Dist: mkdocs>=1.5.3
Provides-Extra: lint
Requires-Dist: djlint==1.34.0; extra == "lint"
Requires-Dist: yamllint==1.32.0; extra == "lint"
Requires-Dist: shot-scraper==1.8; extra == "lint"
Dynamic: license-file
